README.md
setup.py
frasco_redis/__init__.py
frasco_redis/utils.py
frasco_redis.egg-info/PKG-INFO
frasco_redis.egg-info/SOURCES.txt
frasco_redis.egg-info/dependency_links.txt
frasco_redis.egg-info/not-zip-safe
frasco_redis.egg-info/requires.txt
frasco_redis.egg-info/top_level.txt