Metadata-Version: 1.0
Name: frasco-redis
Version: 0.1.7
Summary: Redis integration for Frasco
Home-page: http://github.com/frascoweb/frasco-redis
Author: Maxime Bouroumeau-Fuseau
Author-email: maxime.bouroumeau@gmail.com
License: MIT
Platform: any
